eocanvas/__init__.py
eocanvas/api.py
eocanvas/auth.py
eocanvas/config.py
eocanvas/datatailor/__init__.py
eocanvas/datatailor/chain.py
eocanvas/exceptions.py
eocanvas/http.py
eocanvas/keystore.py
eocanvas/logging.py
eocanvas/processes.py
eocanvas/snap/__init__.py
eocanvas/snap/binning/__init__.py
eocanvas/snap/binning/aggregator_avg.py
eocanvas/snap/binning/aggregator_avg_outlier.py
eocanvas/snap/binning/aggregator_minmax.py
eocanvas/snap/binning/aggregator_on_max_set.py
eocanvas/snap/binning/aggregator_percentile.py
eocanvas/snap/binning/aggregator_sum.py
eocanvas/snap/binning/aggregators.py
eocanvas/snap/binning/binning_band.py
eocanvas/snap/binning/binning_variable.py
eocanvas/snap/binning/binning_variables.py
eocanvas/snap/binning/output_bands.py
eocanvas/snap/data/operators.yaml
eocanvas/snap/graph.py
eocanvas/snap/operator.py
eocanvas/snap/operatorparams.py
eocanvas/snap/operators.json
eocanvas/snap/snap.py
eocanvas/snap/target_band.py
eocanvas/snap/target_band_descriptors.py
eocanvas/snap/utils.py
eocanvas/urls.yaml
eocanvas/utils.py
eocanvas-0.2.7.dist-info/LICENSE.txt
eocanvas-0.2.7.dist-info/METADATA
eocanvas-0.2.7.dist-info/WHEEL
eocanvas-0.2.7.dist-info/RECORD
