Metadata-Version: 2.1
Name: eocanvas
Version: 0.2.7
Summary: A Python wrapper to WEkEO Serverless Functions
License: Apache 2.0
Author: Germano Guerrini
Author-email: germano.guerrini@exprivia.com
Requires-Python: >=3.8.1,<4.0.0
Classifier: License :: Other/Proprietary License
Classifier: Programming Language :: Python :: 3
Classifier: Programming Language :: Python :: 3.9
Classifier: Programming Language :: Python :: 3.10
Classifier: Programming Language :: Python :: 3.11
Classifier: Programming Language :: Python :: 3.12
Classifier: Programming Language :: Python :: 3.13
Provides-Extra: docs
Provides-Extra: optional
Requires-Dist: attrs (>=24.2.0,<25.0.0)
Requires-Dist: cryptography (>=43.0.1,<44.0.0)
Requires-Dist: lxml (>=5.2.2,<6.0.0)
Requires-Dist: pyyaml (>=6.0.1,<7.0.0)
Requires-Dist: requests (>=2.31.0,<3.0.0)
